cmdline_add_args/__init__.py
cmdline_add_args/__main__.py
cmdline_add_args/allure_report_path.py
cmdline_add_args/plugin.py
cmdline_add_args-1.9.6.dist-info/METADATA
cmdline_add_args-1.9.6.dist-info/WHEEL
cmdline_add_args-1.9.6.dist-info/entry_points.txt
cmdline_add_args-1.9.6.dist-info/top_level.txt
cmdline_add_args-1.9.6.dist-info/RECORD
