Metadata-Version: 2.2
Name: cmdline-add-args
Version: 1.9.6
Summary: Pytest plugin for custom argument handling and Allure reporting. This plugin allows you to add arguments before running a test.
Author-email: Yevhen Halitsyn <galitsyn.evgeniy955@gmail.com>
License: MIT
